ein/__init__.py
ein/database.py
ein/edge.py
ein/graph.py
ein/node.py
ein/sql/create-schema.sql
ein/sql/delete-edge.sql
ein/sql/delete-edges.sql
ein/sql/delete-node.sql
ein/sql/delete-nodes.sql
ein/sql/delete-schema.sql
ein/sql/insert-edge.sql
ein/sql/insert-node.sql
ein/sql/select-all-edges.sql
ein/sql/select-all-nodes.sql
ein/sql/select-edge.sql
ein/sql/select-edges.sql
ein/sql/select-node.sql
ein/sql/select-nodes.sql
ein/sql/select-schemas.sql
ein/sql/update-edge.sql
ein/sql/update-node.sql
ein/sql/update-schema.sql
ein_graph-0.0.12.dist-info/LICENSE
ein_graph-0.0.12.dist-info/METADATA
ein_graph-0.0.12.dist-info/WHEEL
ein_graph-0.0.12.dist-info/top_level.txt
ein_graph-0.0.12.dist-info/RECORD
