Metadata-Version: 2.1
Name: ein-graph
Version: 0.0.12
Summary: A graph database implemented in SQLite.
Home-page: https://github.com/mattdood/graph-ein
Author: Matthew Wimberly
Author-email: matthew.wimb@gmail.com
Project-URL: Bug Tracker, https://github.com/mattdood/graph-ein/issues
Classifier: Programming Language :: Python :: 3
Classifier: License :: OSI Approved :: MIT License
Classifier: Operating System :: OS Independent
Requires-Python: >=3.6
License-File: LICENSE
